mpwt/__init__.py
mpwt/__main__.py
mpwt/mpwt_workflow.py
mpwt/pathologic_input.py
mpwt/pwt_wrapper.py
mpwt/results_check.py
mpwt/to_pathologic.py
mpwt/utils.py
mpwt-0.8.7.dist-info/licenses/LICENSE
mpwt-0.8.7.dist-info/METADATA
mpwt-0.8.7.dist-info/WHEEL
mpwt-0.8.7.dist-info/entry_points.txt
mpwt-0.8.7.dist-info/top_level.txt
mpwt-0.8.7.dist-info/RECORD
