Metadata-Version: 2.4
Name: mpwt
Version: 0.8.7
Summary: Multiprocessing for Pathway Tools
Author-email: AuReMe <gem-aureme@inria.fr>
License: LGPL-3.0-or-later
Project-URL: Homepage, https://github.com/AuReMe/mpwt
Project-URL: Changelog, https://github.com/AuReMe/mpwt/blob/main/CHANGELOG.md
Classifier: Development Status :: 4 - Beta
Classifier: Intended Audience :: Science/Research
Classifier: Intended Audience :: Developers
Classifier: Programming Language :: Python :: 3
Requires-Python: >=3.8
License-File: LICENSE
Requires-Dist: biopython>=1.70
Requires-Dist: chardet>=3.0.4
Requires-Dist: gffutils>=0.9
Dynamic: license-file
